virtoloader/__init__.py
virtoloader/data_objs.py
virtoloader/dicom_handler.py
virtoloader/export.py
virtoloader/walkers.py
virtoloader/utils/__init__.py
virtoloader/utils/export_utils.py
virtoloader-1.0.1.dist-info/LICENSE
virtoloader-1.0.1.dist-info/METADATA
virtoloader-1.0.1.dist-info/WHEEL
virtoloader-1.0.1.dist-info/top_level.txt
virtoloader-1.0.1.dist-info/RECORD
