Metadata-Version: 2.1
Name: virtoloader
Version: 1.0.1
Summary: A library with a variety of tools to work with medical imaging data..
Author: André Mourato
Author-email: André Mourato <mourato@virtonomy.io>
License: Apache License 2.0
Classifier: Programming Language :: Python :: 3
Classifier: Programming Language :: Python :: 3.10
Classifier: License :: OSI Approved :: Apache Software License
Classifier: Operating System :: OS Independent
Requires-Python: >=3.10
License-File: LICENSE
Requires-Dist: pydicom
Requires-Dist: numpy
Requires-Dist: pylibjpeg[all]
